pcface.py
pcface-0.3.0.dist-info/LICENSE.md
pcface-0.3.0.dist-info/METADATA
pcface-0.3.0.dist-info/WHEEL
pcface-0.3.0.dist-info/entry_points.txt
pcface-0.3.0.dist-info/top_level.txt
pcface-0.3.0.dist-info/RECORD
