Metadata-Version: 2.1
Name: pcface
Version: 0.3.0
Summary: PC Face - Bitmap arrays for all 256 glyphs of CP437
Author: Susam Pal
License: MIT
Project-URL: homepage, https://github.com/susam/pcface
Keywords: font,cp437,retro
Classifier: Development Status :: 4 - Beta
Classifier: Environment :: Console
Classifier: Intended Audience :: End Users/Desktop
Classifier: Intended Audience :: System Administrators
Classifier: License :: OSI Approved :: MIT License
Classifier: Operating System :: OS Independent
Classifier: Programming Language :: JavaScript
Classifier: Programming Language :: Python :: 3
Classifier: Topic :: Artistic Software
Classifier: Topic :: Multimedia :: Graphics
Classifier: Topic :: Multimedia :: Graphics :: Graphics Conversion
Classifier: Topic :: Text Processing :: Fonts
Classifier: Topic :: Utilities
License-File: LICENSE.md
Requires-Dist: pillow
